{
  "all": {
    "Language": [
      "ar",
      "da",
      "de",
      "de-ba",
      "de-by",
      "de-st",
      "en",
      "gsw",
      "id",
      "it",
      "ja",
      "kk",
      "lt",
      "nap",
      "nl",
      "sr",
      "tr",
      "zh"
    ],
    "slots": [
      71.9,
      82.4,
      82.0,
      52.1,
      53.6,
      48.2,
      95.0,
      31.3,
      81.2,
      82.9,
      45.7,
      59.3,
      68.1,
      60.0,
      87.6,
      75.5,
      64.0,
      77.4
    ],
    "intents": [
      80.6,
      97.2,
      93.4,
      78.2,
      67.4,
      77.4,
      99.4,
      70.0,
      97.8,
      92.0,
      86.8,
      81.2,
      77.6,
      75.0,
      91.4,
      91.2,
      97.2,
      97.2
    ],
    "fully correct": [
      38.2,
      67.0,
      63.0,
      20.6,
      23.0,
      16.8,
      90.6,
      9.4,
      63.4,
      59.4,
      33.6,
      26.2,
      33.0,
      26.6,
      70.4,
      51.6,
      44.0,
      61.2
    ]
  },
  "baseline": {
    "Language": [
      "ar",
      "da",
      "de",
      "de-st",
      "en",
      "id",
      "it",
      "ja",
      "kk",
      "nl",
      "sr",
      "tr",
      "zh"
    ],
    "slots": [
      71.9,
      82.4,
      82.0,
      48.2,
      95.0,
      81.2,
      82.9,
      45.7,
      59.3,
      87.6,
      75.5,
      64.0,
      77.4
    ],
    "intents": [
      80.6,
      97.2,
      93.4,
      77.4,
      99.4,
      97.8,
      92.0,
      86.8,
      81.2,
      91.4,
      91.2,
      97.2,
      97.2
    ],
    "fully correct": [
      38.2,
      67.0,
      63.0,
      16.8,
      90.6,
      63.4,
      59.4,
      33.6,
      26.2,
      70.4,
      51.6,
      44.0,
      61.2
    ]
  },
  "dialects": {
    "Language": [
      "de",
      "de-ba",
      "de-by",
      "de-st",
      "en",
      "gsw"
    ],
    "slots": [
      82.0,
      52.1,
      53.6,
      48.2,
      95.0,
      31.3
    ],
    "intents": [
      93.4,
      78.2,
      67.4,
      77.4,
      99.4,
      70.0
    ],
    "fully correct": [
      63.0,
      20.6,
      23.0,
      16.8,
      90.6,
      9.4
    ]
  }
}